seagoat/__init__.py
seagoat/cache.py
seagoat/cli.py
seagoat/engine.py
seagoat/gitfile.py
seagoat/queue/base_queue.py
seagoat/queue/task_queue.py
seagoat/repository.py
seagoat/result.py
seagoat/server.py
seagoat/sources/chroma.py
seagoat/sources/ripgrep.py
seagoat/utils/cli_display.py
seagoat/utils/config.py
seagoat/utils/debug.py
seagoat/utils/file_reader.py
seagoat/utils/file_types.py
seagoat/utils/generative.py
seagoat/utils/json_file.py
seagoat/utils/server.py
seagoat/utils/wait.py
seagoat-0.54.17.dist-info/LICENSE
seagoat-0.54.17.dist-info/METADATA
seagoat-0.54.17.dist-info/WHEEL
seagoat-0.54.17.dist-info/entry_points.txt
seagoat-0.54.17.dist-info/RECORD
