Metadata-Version: 2.3
Name: seagoat
Version: 0.54.17
Summary: A semantic-code search engine
License: MIT
Author: Daniel Kantor
Author-email: git@daniel-kantor.com
Requires-Python: >=3.10,<3.14
Classifier: License :: OSI Approved :: MIT License
Classifier: Programming Language :: Python :: 3
Classifier: Programming Language :: Python :: 3.10
Classifier: Programming Language :: Python :: 3.11
Classifier: Programming Language :: Python :: 3.12
Classifier: Programming Language :: Python :: 3.13
Requires-Dist: appdirs (>=1.4.4,<2.0.0)
Requires-Dist: blessed (>=1.20.0,<2.0.0)
Requires-Dist: chardet (>=5.2.0,<6.0.0)
Requires-Dist: chromadb (>=1.0.0,<2.0.0)
Requires-Dist: click (>=8.1.3,<9.0.0)
Requires-Dist: deepmerge (>=2.0.0,<3.0.0)
Requires-Dist: flask (>=3.0.0,<4.0.0)
Requires-Dist: gitpython (>=3.1.31,<4.0.0)
Requires-Dist: halo (>=0.0.31,<0.0.32)
Requires-Dist: jsonschema (>=4.19.1,<5.0.0)
Requires-Dist: nest-asyncio (>=1.5.6,<2.0.0)
Requires-Dist: ollama (>=0.4.7,<0.5.0)
Requires-Dist: orjson (>=3.9.5,<4.0.0)
Requires-Dist: psutil (>=7.0.0,<8.0.0)
Requires-Dist: pygments (>=2.15.1,<3.0.0)
Requires-Dist: pyyaml (>=6.0.1,<7.0.0)
Requires-Dist: requests (>=2.31.0,<3.0.0)
Requires-Dist: setuptools (>=75.0.0,<76.0.0)
Requires-Dist: stop-words (>=2018.7.23,<2019.0.0)
Requires-Dist: tqdm (>=4.65.0,<5.0.0)
Requires-Dist: waitress (>=3.0.0,<4.0.0)
